_igeEffekseer.cpython-39-darwin.so
libPVRTexLib.dylib
libfbxsdk.dylib
igeEffekseer/__init__.py
igeEffekseer/Tool/Effekseer.app/Contents/Info.plist
igeEffekseer/Tool/Effekseer.app/Contents/MacOS/script.sh
igeEffekseer/Tool/Effekseer.app/Contents/Resources/Effekseer
igeEffekseer/Tool/Effekseer.app/Contents/Resources/Effekseer.deps.json
igeEffekseer/Tool/Effekseer.app/Contents/Resources/Effekseer.dll
igeEffekseer/Tool/Effekseer.app/Contents/Resources/Effekseer.dll.config
igeEffekseer/Tool/Effekseer.app/Contents/Resources/Effekseer.pdb
igeEffekseer/Tool/Effekseer.app/Contents/Resources/Effekseer.runtimeconfig.dev.json
igeEffekseer/Tool/Effekseer.app/Contents/Resources/Effekseer.runtimeconfig.json
igeEffekseer/Tool/Effekseer.app/Contents/Resources/EffekseerCore.deps.json
igeEffekseer/Tool/Effekseer.app/Contents/Resources/EffekseerCore.dll
igeEffekseer/Tool/Effekseer.app/Contents/Resources/EffekseerCore.pdb
igeEffekseer/Tool/Effekseer.app/Contents/Resources/EffekseerMaterialEditor
igeEffekseer/Tool/Effekseer.app/Contents/Resources/Icon.icns
igeEffekseer/Tool/Effekseer.app/Contents/Resources/IronPython.Modules.dll
igeEffekseer/Tool/Effekseer.app/Contents/Resources/IronPython.SQLite.dll
igeEffekseer/Tool/Effekseer.app/Contents/Resources/IronPython.dll
igeEffekseer/Tool/Effekseer.app/Contents/Resources/Microsoft.CSharp.dll
igeEffekseer/Tool/Effekseer.app/Contents/Resources/Microsoft.Dynamic.dll
igeEffekseer/Tool/Effekseer.app/Contents/Resources/Microsoft.Scripting.Metadata.dll
igeEffekseer/Tool/Effekseer.app/Contents/Resources/Microsoft.Scripting.dll
igeEffekseer/Tool/Effekseer.app/Contents/Resources/Microsoft.VisualBasic.Core.dll
igeEffekseer/Tool/Effekseer.app/Contents/Resources/Microsoft.VisualBasic.dll
igeEffekseer/Tool/Effekseer.app/Contents/Resources/Microsoft.Win32.Primitives.dll
igeEffekseer/Tool/Effekseer.app/Contents/Resources/Microsoft.Win32.Registry.dll
igeEffekseer/Tool/Effekseer.app/Contents/Resources/Newtonsoft.Json.dll
igeEffekseer-0.2.1.dist-info/LICENSE
igeEffekseer-0.2.1.dist-info/METADATA
igeEffekseer-0.2.1.dist-info/WHEEL
igeEffekseer-0.2.1.dist-info/top_level.txt
igeEffekseer-0.2.1.dist-info/RECORD
